{
	"description": "Lists schema major versions applied to a directory. If SchemaArn is provided, lists the minor version.",
	"input_method": "stdin",
	"parameters":{
		
		
		
		
		    
			"schema_arn":{
			   "description": "",
			   "type": "Optional[String[1]]"
			}
			,
		    
			"next_token":{
			   "description": "",
			   "type": "Optional[String[1]]"
			}
			,
		    
			"max_results":{
			   "description": "",
			   "type": "Optional[String[1]]"
			}
			,
		    
			"directory_arn":{
			   "description": "",
			   "type": "Optional[String[1]]"
			}
			
	}
}