{
	"description": "Returns the number of compliant and noncompliant rules for one or more accounts and regions in an aggregator.  The results can return an empty result page, but if you have a nextToken, the results are displayed on the next page. ",
	"input_method": "stdin",
	"parameters":{
		
		
		
		
		    
			"filters":{
			   "description": "",
			   "type": "Optional[String[1]]"
			}
			,
		    
			"group_by_key":{
			   "description": "",
			   "type": "Optional[String[1]]"
			}
			,
		    
			"limit":{
			   "description": "",
			   "type": "Optional[String[1]]"
			}
			,
		    
			"next_token":{
			   "description": "",
			   "type": "Optional[String[1]]"
			}
			,
		    
			"configuration_aggregator_name":{
			   "description": "",
			   "type": "Optional[String[1]]"
			}
			
	}
}