{
	"description": "Creates a network profile.",
	"input_method": "stdin",
	"parameters":{
		
		
		
		
		    
			"uplink_delay_ms":{
			   "description": "",
			   "type": "Optional[String[1]]"
			}
			,
		    
			"uplink_jitter_ms":{
			   "description": "",
			   "type": "Optional[String[1]]"
			}
			,
		    
			"uplink_loss_percent":{
			   "description": "",
			   "type": "Optional[String[1]]"
			}
			,
		    
			"description":{
			   "description": "",
			   "type": "Optional[String[1]]"
			}
			,
		    
			"downlink_loss_percent":{
			   "description": "",
			   "type": "Optional[String[1]]"
			}
			,
		    
			"name":{
			   "description": "",
			   "type": "Optional[String[1]]"
			}
			,
		    
			"project_arn":{
			   "description": "",
			   "type": "Optional[String[1]]"
			}
			,
		    
			"type":{
			   "description": "",
			   "type": "Optional[String[1]]"
			}
			,
		    
			"uplink_bandwidth_bits":{
			   "description": "",
			   "type": "Optional[String[1]]"
			}
			,
		    
			"downlink_bandwidth_bits":{
			   "description": "",
			   "type": "Optional[String[1]]"
			}
			,
		    
			"downlink_delay_ms":{
			   "description": "",
			   "type": "Optional[String[1]]"
			}
			,
		    
			"downlink_jitter_ms":{
			   "description": "",
			   "type": "Optional[String[1]]"
			}
			
	}
}