{
	"description": "Modifies a connection notification for VPC endpoint or VPC endpoint service. You can change the SNS topic for the notification, or the events for which to be notified. ",
	"input_method": "stdin",
	"parameters":{
		
		
		
		
		    
			"connection_events":{
			   "description": "",
			   "type": "Optional[String[1]]"
			}
			,
		    
			"connection_notification_arn":{
			   "description": "",
			   "type": "Optional[String[1]]"
			}
			,
		    
			"connection_notification_id":{
			   "description": "",
			   "type": "Optional[String[1]]"
			}
			,
		    
			"dry_run":{
			   "description": "",
			   "type": "Optional[String[1]]"
			}
			
	}
}