{
	"description": "Describes one or more of your NAT gateways.",
	"input_method": "stdin",
	"parameters":{
		
		
		
		
		    
			"nat_gateway_ids":{
			   "description": "",
			   "type": "Optional[String[1]]"
			}
			,
		    
			"next_token":{
			   "description": "",
			   "type": "Optional[String[1]]"
			}
			,
		    
			"filter":{
			   "description": "",
			   "type": "Optional[String[1]]"
			}
			,
		    
			"max_results":{
			   "description": "",
			   "type": "Optional[String[1]]"
			}
			
	}
}