{
	"description": "Describes the running instances for the specified Spot Fleet.",
	"input_method": "stdin",
	"parameters":{
		
		
		
		
		    
			"spot_fleet_request_id":{
			   "description": "",
			   "type": "Optional[String[1]]"
			}
			,
		    
			"dry_run":{
			   "description": "",
			   "type": "Optional[String[1]]"
			}
			,
		    
			"max_results":{
			   "description": "",
			   "type": "Optional[String[1]]"
			}
			,
		    
			"next_token":{
			   "description": "",
			   "type": "Optional[String[1]]"
			}
			
	}
}