{
	"description": "Deletes a route from a Client VPN endpoint. You can only delete routes that you manually added using the CreateClientVpnRoute action. You cannot delete routes that were automatically added when associating a subnet. To remove routes that have been automatically added, disassociate the target subnet from the Client VPN endpoint.",
	"input_method": "stdin",
	"parameters":{
		
		
		
		
		    
			"client_vpn_endpoint_id":{
			   "description": "",
			   "type": "Optional[String[1]]"
			}
			,
		    
			"destination_cidr_block":{
			   "description": "",
			   "type": "Optional[String[1]]"
			}
			,
		    
			"dry_run":{
			   "description": "",
			   "type": "Optional[String[1]]"
			}
			,
		    
			"target_vpc_subnet_id":{
			   "description": "",
			   "type": "Optional[String[1]]"
			}
			
	}
}