{
	"description": "Create a task set in the specified cluster and service. This is used when a service uses the EXTERNAL deployment controller type. For more information, see Amazon ECS Deployment Types in the Amazon Elastic Container Service Developer Guide.",
	"input_method": "stdin",
	"parameters":{
		
		
		
		
		    
			"service":{
			   "description": "",
			   "type": "Optional[String[1]]"
			}
			,
		    
			"task_definition":{
			   "description": "",
			   "type": "Optional[String[1]]"
			}
			,
		    
			"client_token":{
			   "description": "",
			   "type": "Optional[String[1]]"
			}
			,
		    
			"cluster":{
			   "description": "",
			   "type": "Optional[String[1]]"
			}
			,
		    
			"network_configuration":{
			   "description": "",
			   "type": "Optional[String[1]]"
			}
			,
		    
			"platform_version":{
			   "description": "",
			   "type": "Optional[String[1]]"
			}
			,
		    
			"service_registries":{
			   "description": "",
			   "type": "Optional[String[1]]"
			}
			,
		    
			"external_id":{
			   "description": "",
			   "type": "Optional[String[1]]"
			}
			,
		    
			"launch_type":{
			   "description": "",
			   "type": "Optional[String[1]]"
			}
			,
		    
			"load_balancers":{
			   "description": "",
			   "type": "Optional[String[1]]"
			}
			,
		    
			"scale":{
			   "description": "",
			   "type": "Optional[String[1]]"
			}
			
	}
}