{
	"description": "Creates a cluster. All nodes in the cluster run the same protocol-compliant cache engine software, either Memcached or Redis. This operation is not supported for Redis (cluster mode enabled) clusters.",
	"input_method": "stdin",
	"parameters":{
		
		
		
		
		    
			"engine_version":{
			   "description": "",
			   "type": "Optional[String[1]]"
			}
			,
		    
			"snapshot_window":{
			   "description": "",
			   "type": "Optional[String[1]]"
			}
			,
		    
			"az_mode":{
			   "description": "",
			   "type": "Optional[String[1]]"
			}
			,
		    
			"preferred_availability_zones":{
			   "description": "",
			   "type": "Optional[String[1]]"
			}
			,
		    
			"snapshot_name":{
			   "description": "",
			   "type": "Optional[String[1]]"
			}
			,
		    
			"preferred_maintenance_window":{
			   "description": "",
			   "type": "Optional[String[1]]"
			}
			,
		    
			"auth_token":{
			   "description": "",
			   "type": "Optional[String[1]]"
			}
			,
		    
			"engine":{
			   "description": "",
			   "type": "Optional[String[1]]"
			}
			,
		    
			"cache_parameter_group_name":{
			   "description": "",
			   "type": "Optional[String[1]]"
			}
			,
		    
			"replication_group_id":{
			   "description": "",
			   "type": "Optional[String[1]]"
			}
			,
		    
			"num_cache_nodes":{
			   "description": "",
			   "type": "Optional[String[1]]"
			}
			,
		    
			"cache_node_type":{
			   "description": "",
			   "type": "Optional[String[1]]"
			}
			,
		    
			"tags":{
			   "description": "",
			   "type": "Optional[String[1]]"
			}
			,
		    
			"cache_subnet_group_name":{
			   "description": "",
			   "type": "Optional[String[1]]"
			}
			,
		    
			"auto_minor_version_upgrade":{
			   "description": "",
			   "type": "Optional[String[1]]"
			}
			,
		    
			"cache_security_group_names":{
			   "description": "",
			   "type": "Optional[String[1]]"
			}
			,
		    
			"snapshot_arns":{
			   "description": "",
			   "type": "Optional[String[1]]"
			}
			,
		    
			"port":{
			   "description": "",
			   "type": "Optional[String[1]]"
			}
			,
		    
			"preferred_availability_zone":{
			   "description": "",
			   "type": "Optional[String[1]]"
			}
			,
		    
			"notification_topic_arn":{
			   "description": "",
			   "type": "Optional[String[1]]"
			}
			,
		    
			"security_group_ids":{
			   "description": "",
			   "type": "Optional[String[1]]"
			}
			,
		    
			"snapshot_retention_limit":{
			   "description": "",
			   "type": "Optional[String[1]]"
			}
			,
		    
			"cache_cluster_id":{
			   "description": "",
			   "type": "Optional[String[1]]"
			}
			
	}
}