{
	"description": "Modifies the health checks used when evaluating the health state of the targets in the specified target group. To monitor the health of the targets, use DescribeTargetHealth.",
	"input_method": "stdin",
	"parameters":{
		
		
		
		
		    
			"health_check_enabled":{
			   "description": "",
			   "type": "Optional[String[1]]"
			}
			,
		    
			"health_check_port":{
			   "description": "",
			   "type": "Optional[String[1]]"
			}
			,
		    
			"health_check_timeout_seconds":{
			   "description": "",
			   "type": "Optional[String[1]]"
			}
			,
		    
			"target_group_arn":{
			   "description": "",
			   "type": "Optional[String[1]]"
			}
			,
		    
			"unhealthy_threshold_count":{
			   "description": "",
			   "type": "Optional[String[1]]"
			}
			,
		    
			"health_check_interval_seconds":{
			   "description": "",
			   "type": "Optional[String[1]]"
			}
			,
		    
			"health_check_path":{
			   "description": "",
			   "type": "Optional[String[1]]"
			}
			,
		    
			"health_check_protocol":{
			   "description": "",
			   "type": "Optional[String[1]]"
			}
			,
		    
			"healthy_threshold_count":{
			   "description": "",
			   "type": "Optional[String[1]]"
			}
			,
		    
			"matcher":{
			   "description": "",
			   "type": "Optional[String[1]]"
			}
			
	}
}