{
	"description": "Deletes the specified certificate. A certificate cannot be deleted if it has a policy attached to it or if its status is set to ACTIVE. To delete a certificate, first use the DetachPrincipalPolicy API to detach all policies. Next, use the UpdateCertificate API to set the certificate to the INACTIVE status.",
	"input_method": "stdin",
	"parameters":{
		
		
		
		
		    
			"certificate_id":{
			   "description": "",
			   "type": "Optional[String[1]]"
			}
			,
		    
			"force_delete":{
			   "description": "",
			   "type": "Optional[String[1]]"
			}
			
	}
}