{
	"description": "Deletes a CloudWatch log stream from an application. For more information about using CloudWatch log streams with Amazon Kinesis Analytics applications, see Working with Amazon CloudWatch Logs.",
	"input_method": "stdin",
	"parameters":{
		
		
		
		
		    
			"current_application_version_id":{
			   "description": "",
			   "type": "Optional[String[1]]"
			}
			,
		    
			"cloud_watch_logging_option_id":{
			   "description": "",
			   "type": "Optional[String[1]]"
			}
			,
		    
			"application_name":{
			   "description": "",
			   "type": "Optional[String[1]]"
			}
			
	}
}