{
	"description": "Returns a list of DB log files for the DB instance.",
	"input_method": "stdin",
	"parameters":{
		
		
		
		
		    
			"file_size":{
			   "description": "",
			   "type": "Optional[String[1]]"
			}
			,
		    
			"filters":{
			   "description": "",
			   "type": "Optional[String[1]]"
			}
			,
		    
			"max_records":{
			   "description": "",
			   "type": "Optional[String[1]]"
			}
			,
		    
			"marker":{
			   "description": "",
			   "type": "Optional[String[1]]"
			}
			,
		    
			"db_instance_identifier":{
			   "description": "",
			   "type": "Optional[String[1]]"
			}
			,
		    
			"filename_contains":{
			   "description": "",
			   "type": "Optional[String[1]]"
			}
			,
		    
			"file_last_written":{
			   "description": "",
			   "type": "Optional[String[1]]"
			}
			
	}
}