{
	"description": "Inserts or deletes GeoMatchConstraint objects in an GeoMatchSet. For each GeoMatchConstraint object, you specify the following values:    Whether to insert or delete the object from the array. If you want to change an GeoMatchConstraint object, you delete the existing object and add a new one.   The Type. The only valid value for Type is Country.   The Value, which is a two character code for the country to add to the GeoMatchConstraint object. Valid codes are listed in GeoMatchConstraint$Value.   To create and configure an GeoMatchSet, perform the following steps:   Submit a CreateGeoMatchSet request.   Use GetChangeToken to get the change token that you provide in the ChangeToken parameter of an UpdateGeoMatchSet request.   Submit an UpdateGeoMatchSet request to specify the country that you want AWS WAF to watch for.   When you update an GeoMatchSet, you specify the country that you want to add and/or the country that you want to delete. If you want to change a country, you delete the existing country and add the new one. For more information about how to use the AWS WAF API to allow or block HTTP requests, see the AWS WAF Developer Guide.",
	"input_method": "stdin",
	"parameters":{
		
		
		
		
		    
			"geo_match_set_id":{
			   "description": "",
			   "type": "Optional[String[1]]"
			}
			,
		    
			"change_token":{
			   "description": "",
			   "type": "Optional[String[1]]"
			}
			,
		    
			"updates":{
			   "description": "",
			   "type": "Optional[String[1]]"
			}
			
	}
}